{
    "Ar36": {
        "error": 0.0017045839523078092,
        "error_type": "SEM",
        "filter_outliers_dict": {
            "filter_outliers": true,
            "iterations": 1,
            "std_devs": 3,
            "use_iqr_filtering": false,
            "use_standard_deviation_filtering": false
        },
        "fit": "linear",
        "fn": 24,
        "include_baseline_error": true,
        "n": 24,
        "outlier_excluded": [],
        "reviewed": true,
        "user_excluded": [],
        "value": 0.013751740931550505
    },
    "Ar37": {
        "error": 0.02631203600535619,
        "error_type": "SEM",
        "filter_outliers_dict": {
            "filter_outliers": true,
            "iterations": 1,
            "std_devs": 3,
            "use_iqr_filtering": false,
            "use_standard_deviation_filtering": false
        },
        "fit": "linear",
        "fn": 24,
        "include_baseline_error": true,
        "n": 24,
        "outlier_excluded": [],
        "reviewed": true,
        "user_excluded": [],
        "value": -0.030142703219334963
    },
    "Ar38": {
        "error": 0.020156989969964047,
        "error_type": "SEM",
        "filter_outliers_dict": {
            "filter_outliers": true,
            "iterations": 1,
            "std_devs": 3,
            "use_iqr_filtering": false,
            "use_standard_deviation_filtering": false
        },
        "fit": "linear",
        "fn": 24,
        "include_baseline_error": true,
        "n": 24,
        "outlier_excluded": [],
        "reviewed": true,
        "user_excluded": [],
        "value": 0.025188192604240187
    },
    "Ar39": {
        "error": 0.05470480885267149,
        "error_type": "SEM",
        "filter_outliers_dict": {
            "filter_outliers": true,
            "iterations": 1,
            "std_devs": 3,
            "use_iqr_filtering": false,
            "use_standard_deviation_filtering": false
        },
        "fit": "linear",
        "fn": 24,
        "include_baseline_error": true,
        "n": 24,
        "outlier_excluded": [],
        "reviewed": true,
        "user_excluded": [],
        "value": 0.046695637088227084
    },
    "Ar40": {
        "error": 0.05727609134689382,
        "error_type": "SEM",
        "filter_outliers_dict": {
            "filter_outliers": true,
            "iterations": 1,
            "std_devs": 3,
            "use_iqr_filtering": false,
            "use_standard_deviation_filtering": false
        },
        "fit": "linear",
        "fn": 24,
        "include_baseline_error": true,
        "n": 24,
        "outlier_excluded": [],
        "reviewed": true,
        "user_excluded": [],
        "value": 3.829044611234508
    },
    "Ar41": {
        "error": 0.3189411248019404,
        "error_type": "SEM",
        "filter_outliers_dict": {
            "filter_outliers": true,
            "iterations": 1,
            "std_devs": 2
        },
        "fit": "linear",
        "value": -0.4401296225137791
    }
}